llm_cluster.py
llm_cluster-0.2.dist-info/LICENSE
llm_cluster-0.2.dist-info/METADATA
llm_cluster-0.2.dist-info/WHEEL
llm_cluster-0.2.dist-info/entry_points.txt
llm_cluster-0.2.dist-info/top_level.txt
llm_cluster-0.2.dist-info/RECORD
