Metadata-Version: 2.1
Name: llm-cluster
Version: 0.2
Summary: LLM plugin for clustering embeddings
Author: Simon Willison
License: Apache-2.0
Project-URL: Homepage, https://github.com/simonw/llm-cluster
Project-URL: Changelog, https://github.com/simonw/llm-cluster/releases
Project-URL: Issues, https://github.com/simonw/llm-cluster/issues
Project-URL: CI, https://github.com/simonw/llm-cluster/actions
Classifier: License :: OSI Approved :: Apache Software License
License-File: LICENSE
Requires-Dist: llm >=0.9
Requires-Dist: scikit-learn
Provides-Extra: test
Requires-Dist: pytest ; extra == 'test'
